<?xml version="1.0" encoding="ISO-8859-1"?>
<EnvioDTE xmlns="http://www.sii.cl/SiiDte" xmlns:xsi="http://www.w3.org/2001/XMLSchema-instance" xsi:schemaLocation="http://www.sii.cl/SiiDte EnvioDTE_v10.xsd" version="1.0">
  <SetDTE ID="SetDoc">
    <Caratula version="1.0">
      <RutEmisor>76019353-4</RutEmisor>
      <RutEnvia>6419970-6</RutEnvia>
      <RutReceptor>60803000-K</RutReceptor>
      <FchResol>2014-08-22</FchResol>
      <NroResol>80</NroResol>
      <TmstFirmaEnv>2016-08-25T16:02:51</TmstFirmaEnv>
      <SubTotDTE>
        <TpoDTE>33</TpoDTE>
        <NroDTE>1</NroDTE>
      </SubTotDTE>
    </Caratula>
    <DTE version="1.0">
  <Documento ID="T33F1283">
    <Encabezado>
      <IdDoc>
        <TipoDTE>33</TipoDTE>
        <Folio>1283</Folio>
        <FchEmis>2016-08-25</FchEmis>
      </IdDoc>
      <Emisor>
        <RUTEmisor>76019353-4</RUTEmisor>
        <RznSoc>SOCIEDAD COMERCIAL DEIK Y COMPA—IA LIMITADA</RznSoc>
        <GiroEmis>VENTAS AL POR MENOR DE OTROS PRODUCTOS EN ALMACENES ESPECIALIZADOS N.C.P.</GiroEmis>
        <Acteco>523999</Acteco>
        <DirOrigen>8 ORIENTE No.1378</DirOrigen>
        <CmnaOrigen>TALCA</CmnaOrigen>
      </Emisor>
      <Receptor>
        <RUTRecep>95439000-4</RUTRecep>
        <RznSocRecep>SOC. CLINICA DEL MAULE S.A</RznSocRecep>
        <GiroRecep>HOSPITALES Y CLIçNICAS</GiroRecep>
        <DirRecep>4 NORTE NO. 1640</DirRecep>
        <CmnaRecep>TALCA</CmnaRecep>
      </Receptor>
      <Totales>
        <MntNeto>163213</MntNeto>
        <TasaIVA>19</TasaIVA>
        <IVA>31010</IVA>
        <MntTotal>194223</MntTotal>
      </Totales>
    </Encabezado>
    <Detalle>
      <NroLinDet>1</NroLinDet>
      <NmbItem>AMPOLLETA ECO. HALOG. CLASICA 52W LC WESTINGH</NmbItem>
      <QtyItem>5.000</QtyItem>
      <PrcItem>790</PrcItem>
      <MontoItem>3950</MontoItem>
    </Detalle>
    <Detalle>
      <NroLinDet>2</NroLinDet>
      <NmbItem>TELEFONO M/LIBRES BLANCO DTI                 </NmbItem>
      <QtyItem>3.000</QtyItem>
      <PrcItem>8042</PrcItem>
      <MontoItem>24126</MontoItem>
    </Detalle>
    <Detalle>
      <NroLinDet>3</NroLinDet>
      <NmbItem>CABLE LIBRE HALOGENO 2,5 MM2 BCO.            </NmbItem>
      <QtyItem>20.000</QtyItem>
      <PrcItem>178.15</PrcItem>
      <MontoItem>3563</MontoItem>
    </Detalle>
    <Detalle>
      <NroLinDet>4</NroLinDet>
      <NmbItem>CABLE LIBRE HALOGENO 2,5 MM2 ROJO            </NmbItem>
      <QtyItem>20.000</QtyItem>
      <PrcItem>178.15</PrcItem>
      <MontoItem>3563</MontoItem>
    </Detalle>
    <Detalle>
      <NroLinDet>5</NroLinDet>
      <NmbItem>MODULO ENCHUFE 10-16A MAGIC 5180 BTICINO     </NmbItem>
      <QtyItem>10.000</QtyItem>
      <PrcItem>3329.4</PrcItem>
      <MontoItem>33294</MontoItem>
    </Detalle>
    <Detalle>
      <NroLinDet>6</NroLinDet>
      <NmbItem>SOPORTE PLASTICO MAGIC 503/R BTICINO         </NmbItem>
      <QtyItem>4.000</QtyItem>
      <PrcItem>731</PrcItem>
      <MontoItem>2924</MontoItem>
    </Detalle>
    <Detalle>
      <NroLinDet>7</NroLinDet>
      <NmbItem>MOLDURA ELECTRICA 20 X 10 C/ ADHESIVO KALOP  </NmbItem>
      <QtyItem>2.000</QtyItem>
      <PrcItem>1164.5</PrcItem>
      <MontoItem>2329</MontoItem>
    </Detalle>
    <Detalle>
      <NroLinDet>8</NroLinDet>
      <NmbItem>AMPOLLETA AHORRO ESPIRAL 14W E27 2700K GLOBAL</NmbItem>
      <QtyItem>40.000</QtyItem>
      <PrcItem>1350.425</PrcItem>
      <MontoItem>54017</MontoItem>
    </Detalle>
    <Detalle>
      <NroLinDet>9</NroLinDet>
      <NmbItem>ALARGADOR 5T. C/INT. 5MT NEG. RITTING        </NmbItem>
      <QtyItem>2.000</QtyItem>
      <PrcItem>4659.5</PrcItem>
      <MontoItem>9319</MontoItem>
    </Detalle>
    <Detalle>
      <NroLinDet>10</NroLinDet>
      <NmbItem>AMPOLLETA AHORRO TRITUB. 15W E27 6400K GLOBAL</NmbItem>
      <QtyItem>10.000</QtyItem>
      <PrcItem>1150.4</PrcItem>
      <MontoItem>11504</MontoItem>
    </Detalle>
    <Detalle>
      <NroLinDet>11</NroLinDet>
      <NmbItem>CABLE LIBRE HALOGENO 2,5 MM2 VERD.           </NmbItem>
      <QtyItem>20.000</QtyItem>
      <PrcItem>178.15</PrcItem>
      <MontoItem>3563</MontoItem>
    </Detalle>
    <Detalle>
      <NroLinDet>12</NroLinDet>
      <NmbItem>BALLAST ELECTR. 2X36W BYP                    </NmbItem>
      <QtyItem>2.000</QtyItem>
      <PrcItem>5530.5</PrcItem>
      <MontoItem>11061</MontoItem>
    </Detalle>
    <TED version="1.0">
  <DD>
    <RE>76019353-4</RE>
    <TD>33</TD>
    <F>1283</F>
    <FE>2016-08-25</FE>
    <RR>95439000-4</RR>
    <RSR>SOC. CLINICA DEL MAULE S.A</RSR>
    <MNT>194223</MNT>
    <IT1>AMPOLLETA ECO. HALOG. CLASICA 52W LC WES</IT1>
    <CAF version="1.0">
<DA>
<RE>76019353-4</RE>
<RS>SOCIEDAD COMERCIAL DEIK Y COMPANIA LIMIT</RS>
<TD>33</TD>
<RNG><D>1</D><H>1400</H></RNG>
<FA>2016-07-24</FA>
<RSAPK><M>5JyzXxYDEh0apdnsx/HewBVYt7V6MyHgVX6N0xfkcG+MEKkPV2clcrmu4FL4AiV4+cOAOjUoCzy7q+g1rEzXKw==</M><E>Aw==</E></RSAPK>
<IDK>300</IDK>
</DA>
<FRMA algoritmo="SHA1withRSA">lwVpid7fXAR4S68/PVugt9JIgomHBTQ25n2/uOFN/xj2K6fGZTRrjAOl8H/qZgcoM89tOLe0zBs0qSO2HpnnYA==</FRMA>
</CAF>
    <TSTED>2016-08-25T16:02:51</TSTED>
  </DD>
  <FRMT algoritmo="SHA1withRSA">eBX9wSnceiuuRPpbxyrcDTHnqWgDF+gOY9YjyJWUT5GwvpiHfCs3OuudfmQooXyuhheGUmRLQBmZYt+Lu4ZnDw==</FRMT>
</TED>
  <TmstFirma>2016-08-25T16:02:51</TmstFirma></Documento>
<Signature xmlns="http://www.w3.org/2000/09/xmldsig#"><SignedInfo xmlns="http://www.w3.org/2000/09/xmldsig#"><CanonicalizationMethod Algorithm="http://www.w3.org/TR/2001/REC-xml-c14n-20010315"/><SignatureMethod Algorithm="http://www.w3.org/2000/09/xmldsig#rsa-sha1"/><Reference URI="#T33F1283"><Transforms><Transform Algorithm="http://www.w3.org/2000/09/xmldsig#enveloped-signature"/></Transforms><DigestMethod Algorithm="http://www.w3.org/2000/09/xmldsig#sha1"/><DigestValue>ig5fpkGJ4QlfN+Ff6/ViDKbSQn4=</DigestValue></Reference></SignedInfo><SignatureValue>VBf4rO1g0OsIUS7VIwkS9Rd7JI6wP0WezeuuZYnb7cyLHlQW6/0ZN3OSKI6Lyl8W
t+pTb2UOFziHdgmFbZdPREqnsyZCihR+SABkiVHRTT5av7lKCuko5aD+ncwzSZJj
9CCJ7jtPRaXrAf1xtwep4gzAc6txQzaNZRtqWzY70t0MQ+v824ddpmFGMoQgHaET
dtB2V9mhTraF9y/6pqy10IO0oTTQ6lvj3kt8ynm+lyf9/dMbfZv79Z8XWM178ReV
XL0yG7Knnvvlp3m2BguuB1XbMWEu3DYCAGyAgCn8/3nOcooBxIRSghPKStht8W7k
16tVFrbso5bUhytWEBwV9Q==</SignatureValue><KeyInfo><KeyValue><RSAKeyValue><Modulus>n88xfYaBMyJlx3FwqC2i99RXpfdN2FhD7k2gAJ0qQS77b2SDXcXcsz84Newy9+dN
ctkfrZ2NaUHgZMY/VZAUj+THflJyG5iP63l1aVkQF2O9lqEsdmJQ2icCzWMzqEZ6
rRYF35FtZxpQkEMhorOvJNXLKAOnUW93TmnU+wOumRHpbxoiehCheYd4ZhO+zPNg
iZk6zzDqekcJ86Atj27P21VlXYTFVWdYFIhVp2r5e9oS8ZtmdSNKNC7y68UH/mzq
XcRvJM6RGiTMt7KFbc5kMlfDs5UgeBudpz6PFbuKm1lLJn808dVXQbFlHcxpPYZa
N7g1tzQOM5CP25bZrH/sKw==</Modulus><Exponent>AQAB</Exponent></RSAKeyValue></KeyValue><X509Data><X509Certificate>MIIFzDCCBLSgAwIBAgICSPAwDQYJKoZIhvcNAQEFBQAwgaYxCzAJBgNVBAYTAkNM
MRgwFgYDVQQKEw9BY2VwdGEuY29tIFMuQS4xSDBGBgNVBAMTP0FjZXB0YS5jb20g
QXV0b3JpZGFkIENlcnRpZmljYWRvcmEgQ2xhc2UgMiBQZXJzb25hIE5hdHVyYWwg
LSBHMzEeMBwGCSqGSIb3DQEJARYPaW5mb0BhY2VwdGEuY29tMRMwEQYDVQQFEwo5
NjkxOTA1MC04MB4XDTE2MDYxMDE1NDYyOVoXDTE5MDYxMDE1NDYyOVowgYAxCzAJ
BgNVBAYTAkNMMRgwFgYDVQQMEw9QRVJTT05BIE5BVFVSQUwxIDAeBgNVBAMTF01P
SVNFUyBKT1JHRSBERUlLIE5VTkVaMSEwHwYJKoZIhvcNAQkBFhJjZGRlaWtAaG90
bWFpbC5jb20xEjAQBgNVBAUTCTY0MTk5NzAtNjCCASIwDQYJKoZIhvcNAQEBBQAD
ggEPADCCAQoCggEBAJ/PMX2GgTMiZcdxcKgtovfUV6X3TdhYQ+5NoACdKkEu+29k
g13F3LM/ODXsMvfnTXLZH62djWlB4GTGP1WQFI/kx35SchuYj+t5dWlZEBdjvZah
LHZiUNonAs1jM6hGeq0WBd+RbWcaUJBDIaKzryTVyygDp1Fvd05p1PsDrpkR6W8a
InoQoXmHeGYTvszzYImZOs8w6npHCfOgLY9uz9tVZV2ExVVnWBSIVadq+XvaEvGb
ZnUjSjQu8uvFB/5s6l3EbyTOkRokzLeyhW3OZDJXw7OVIHgbnac+jxW7iptZSyZ/
NPHVV0GxZR3MaT2GWje4Nbc0DjOQj9uW2ax/7CsCAwEAAaOCAiYwggIiMB8GA1Ud
IwQYMBaAFEAkGj2pMXqFd3o9nnKTOYTlQDgZMB0GA1UdDgQWBBSZ3M8Cee507TAW
lmGQS2RUC5KhjTALBgNVHQ8EBAMCBPAwHQYDVR0lBBYwFAYIKwYBBQUHAwIGCCsG
AQUFBwMEMBEGCWCGSAGG+EIBAQQEAwIFoDBuBgNVHSAEZzBlMGMGCisGAQQBtWuH
agowVTAoBggrBgEFBQcCARYcaHR0cDovL3d3dy5hY2VwdGEuY29tL0NQUy1HMzAp
BggrBgEFBQcCAjAdMBYWD0FjZXB0YS5jb20gUy5BLjADAgEJGgNUQkQwWgYDVR0S
BFMwUaAYBggrBgEEAcEBAqAMFgo5NjkxOTA1MC04oCQGCCsGAQUFBwgDoBgwFgwK
OTY5MTkwNTAtOAYIKwYBBAHBAQKBD2luZm9AYWNlcHRhLmNvbTBbBgNVHREEVDBS
oBcGCCsGAQQBwQEBoAsWCTY0MTk5NzAtNqAjBggrBgEFBQcIA6AXMBUMCTY0MTk5
NzAtNgYIKwYBBAHBAQKBEmNkZGVpa0Bob3RtYWlsLmNvbTA/BggrBgEFBQcBAQQz
MDEwLwYIKwYBBQUHMAGGI2h0dHA6Ly9vY3NwLmFjZXB0YS5jb20vQ2xhc2UzQmlv
LUczMDcGA1UdHwQwMC4wLKAqoCiGJmh0dHA6Ly9jcmwuYWNlcHRhLmNvbS9DbGFz
ZTNCaW8tRzMuY3JsMA0GCSqGSIb3DQEBBQUAA4IBAQB5tqWVS14g+ZKL77ILM6a1
q6TYoGoEasJbaPqhWOyFTgCIJb7S50cX6IQWbOxdWm3mn5SIvSXeKdFNX5hT3QYu
T/9N2JEjjbUrdKQ0AqFK7YpFuCrFEklpchAi0wrVhMBQ67Kqbmo0X+BYiFvHGolT
tbHLYeGskyDu8DCjYyRG+8b86zB97sdp0NLdk9pzqwxBFU7cRCoj/o3j9fmZvq8Z
IbfLJBTGN5p+uaF6k6Ys1/X4PDBGRCuUrs9AEeNHO7okWXg9j/MHvA0od25v91Tj
8gsc+eCFKtrOoa0BMwmWPbuiYuuVnOX/RFVDywfv2WHEW8Pc5ajAmZ7bvq/AuOqT</X509Certificate></X509Data></KeyInfo></Signature></DTE>
  </SetDTE>
<Signature xmlns="http://www.w3.org/2000/09/xmldsig#"><SignedInfo xmlns="http://www.w3.org/2000/09/xmldsig#" xmlns:xsi="http://www.w3.org/2001/XMLSchema-instance"><CanonicalizationMethod Algorithm="http://www.w3.org/TR/2001/REC-xml-c14n-20010315"/><SignatureMethod Algorithm="http://www.w3.org/2000/09/xmldsig#rsa-sha1"/><Reference URI="#SetDoc"><Transforms><Transform Algorithm="http://www.w3.org/2000/09/xmldsig#enveloped-signature"/></Transforms><DigestMethod Algorithm="http://www.w3.org/2000/09/xmldsig#sha1"/><DigestValue>/dQdHuPbN2xkE8P2JML/f5idOm0=</DigestValue></Reference></SignedInfo><SignatureValue>LcajAz+bM1CVscrDbeVJLNqfpCYl3qkZZv3ylZTGSLaJk05v5Mub/A/+c5pc1GUt
PQ1AKqYDtH6Fq2/lvhnzL7JhmzTUQAGOMJag1T22nj94as1Nj68sZXVFEwco2z2/
l0UEWyOFBkAMyC1HTiaq+Cd9godTnIPE2Z8AnKRJVtjwObBbX0R9eD6D4u3PEcBJ
lhTznjvgWRtYkTBM3/FuFBdMMRLCUgJs0bhuUWnv5Cvvc5afE9vdbP/wkzNIkQbq
u3oFKop5+qsYXRNqRaq7oMcLexh3eSsc6JLI9F8uxA0l8snh8G9wFbFqJwILVUe5
09F1I1shvvOtxUSxCfzV2w==</SignatureValue><KeyInfo><KeyValue><RSAKeyValue><Modulus>n88xfYaBMyJlx3FwqC2i99RXpfdN2FhD7k2gAJ0qQS77b2SDXcXcsz84Newy9+dN
ctkfrZ2NaUHgZMY/VZAUj+THflJyG5iP63l1aVkQF2O9lqEsdmJQ2icCzWMzqEZ6
rRYF35FtZxpQkEMhorOvJNXLKAOnUW93TmnU+wOumRHpbxoiehCheYd4ZhO+zPNg
iZk6zzDqekcJ86Atj27P21VlXYTFVWdYFIhVp2r5e9oS8ZtmdSNKNC7y68UH/mzq
XcRvJM6RGiTMt7KFbc5kMlfDs5UgeBudpz6PFbuKm1lLJn808dVXQbFlHcxpPYZa
N7g1tzQOM5CP25bZrH/sKw==</Modulus><Exponent>AQAB</Exponent></RSAKeyValue></KeyValue><X509Data><X509Certificate>MIIFzDCCBLSgAwIBAgICSPAwDQYJKoZIhvcNAQEFBQAwgaYxCzAJBgNVBAYTAkNM
MRgwFgYDVQQKEw9BY2VwdGEuY29tIFMuQS4xSDBGBgNVBAMTP0FjZXB0YS5jb20g
QXV0b3JpZGFkIENlcnRpZmljYWRvcmEgQ2xhc2UgMiBQZXJzb25hIE5hdHVyYWwg
LSBHMzEeMBwGCSqGSIb3DQEJARYPaW5mb0BhY2VwdGEuY29tMRMwEQYDVQQFEwo5
NjkxOTA1MC04MB4XDTE2MDYxMDE1NDYyOVoXDTE5MDYxMDE1NDYyOVowgYAxCzAJ
BgNVBAYTAkNMMRgwFgYDVQQMEw9QRVJTT05BIE5BVFVSQUwxIDAeBgNVBAMTF01P
SVNFUyBKT1JHRSBERUlLIE5VTkVaMSEwHwYJKoZIhvcNAQkBFhJjZGRlaWtAaG90
bWFpbC5jb20xEjAQBgNVBAUTCTY0MTk5NzAtNjCCASIwDQYJKoZIhvcNAQEBBQAD
ggEPADCCAQoCggEBAJ/PMX2GgTMiZcdxcKgtovfUV6X3TdhYQ+5NoACdKkEu+29k
g13F3LM/ODXsMvfnTXLZH62djWlB4GTGP1WQFI/kx35SchuYj+t5dWlZEBdjvZah
LHZiUNonAs1jM6hGeq0WBd+RbWcaUJBDIaKzryTVyygDp1Fvd05p1PsDrpkR6W8a
InoQoXmHeGYTvszzYImZOs8w6npHCfOgLY9uz9tVZV2ExVVnWBSIVadq+XvaEvGb
ZnUjSjQu8uvFB/5s6l3EbyTOkRokzLeyhW3OZDJXw7OVIHgbnac+jxW7iptZSyZ/
NPHVV0GxZR3MaT2GWje4Nbc0DjOQj9uW2ax/7CsCAwEAAaOCAiYwggIiMB8GA1Ud
IwQYMBaAFEAkGj2pMXqFd3o9nnKTOYTlQDgZMB0GA1UdDgQWBBSZ3M8Cee507TAW
lmGQS2RUC5KhjTALBgNVHQ8EBAMCBPAwHQYDVR0lBBYwFAYIKwYBBQUHAwIGCCsG
AQUFBwMEMBEGCWCGSAGG+EIBAQQEAwIFoDBuBgNVHSAEZzBlMGMGCisGAQQBtWuH
agowVTAoBggrBgEFBQcCARYcaHR0cDovL3d3dy5hY2VwdGEuY29tL0NQUy1HMzAp
BggrBgEFBQcCAjAdMBYWD0FjZXB0YS5jb20gUy5BLjADAgEJGgNUQkQwWgYDVR0S
BFMwUaAYBggrBgEEAcEBAqAMFgo5NjkxOTA1MC04oCQGCCsGAQUFBwgDoBgwFgwK
OTY5MTkwNTAtOAYIKwYBBAHBAQKBD2luZm9AYWNlcHRhLmNvbTBbBgNVHREEVDBS
oBcGCCsGAQQBwQEBoAsWCTY0MTk5NzAtNqAjBggrBgEFBQcIA6AXMBUMCTY0MTk5
NzAtNgYIKwYBBAHBAQKBEmNkZGVpa0Bob3RtYWlsLmNvbTA/BggrBgEFBQcBAQQz
MDEwLwYIKwYBBQUHMAGGI2h0dHA6Ly9vY3NwLmFjZXB0YS5jb20vQ2xhc2UzQmlv
LUczMDcGA1UdHwQwMC4wLKAqoCiGJmh0dHA6Ly9jcmwuYWNlcHRhLmNvbS9DbGFz
ZTNCaW8tRzMuY3JsMA0GCSqGSIb3DQEBBQUAA4IBAQB5tqWVS14g+ZKL77ILM6a1
q6TYoGoEasJbaPqhWOyFTgCIJb7S50cX6IQWbOxdWm3mn5SIvSXeKdFNX5hT3QYu
T/9N2JEjjbUrdKQ0AqFK7YpFuCrFEklpchAi0wrVhMBQ67Kqbmo0X+BYiFvHGolT
tbHLYeGskyDu8DCjYyRG+8b86zB97sdp0NLdk9pzqwxBFU7cRCoj/o3j9fmZvq8Z
IbfLJBTGN5p+uaF6k6Ys1/X4PDBGRCuUrs9AEeNHO7okWXg9j/MHvA0od25v91Tj
8gsc+eCFKtrOoa0BMwmWPbuiYuuVnOX/RFVDywfv2WHEW8Pc5ajAmZ7bvq/AuOqT</X509Certificate></X509Data></KeyInfo></Signature></EnvioDTE>
